{"cameraMode":{"drawMode":0,"name":"Shaded","section":"Shading Mode"},"sceneLighting":true,"audioPlay":false,"sceneViewState":{"showFog":true,"showMaterialUpdate":false,"showSkybox":true,"showFlares":true,"showImageEffects":true,"showParticleSystems":true},"in2DMode":false,"pivot":{"x":8.675156593322754,"y":-28.718982696533204,"z":11.129152297973633},"rotation":{"x":0.49190908670425417,"y":-0.5068953633308411,"z":0.4753515124320984,"w":0.5245462656021118},"size":56.67673873901367,"orthographic":false}